gaiweb/__init__.py
gaiweb/gaiweb.py
gaiweb-2.0.0.dist-info/METADATA
gaiweb-2.0.0.dist-info/WHEEL
gaiweb-2.0.0.dist-info/entry_points.txt
gaiweb-2.0.0.dist-info/top_level.txt
gaiweb-2.0.0.dist-info/RECORD
