Metadata-Version: 2.1
Name: gaiweb
Version: 2.0.0
Summary: gaiweb是一个基于 Flask 的轻量级 Gemini 流式聊天本地应用 
Home-page: https://github.com/pythonxueba
Author: python_xueba
Classifier: Programming Language :: Python :: 3
Classifier: License :: OSI Approved :: MIT License
Classifier: Operating System :: OS Independent
Classifier: Topic :: Internet :: WWW/HTTP :: Dynamic Content
Requires-Python: >=3.8
Requires-Dist: Flask>=2.0
Requires-Dist: flask-cors
Requires-Dist: requests
Requires-Dist: beautifulsoup4
